LICENSE
torchvf/__init__.py
torchvf/dataloaders/__init__.py
torchvf/dataloaders/bpcis.py
torchvf/dataloaders/dataloader.py
torchvf/dataloaders/sartorius.py
torchvf/losses/__init__.py
torchvf/losses/dice.py
torchvf/losses/ivp_loss.py
torchvf/losses/tversky.py
torchvf/metrics/__init__.py
torchvf/metrics/f1.py
torchvf/metrics/iou.py
torchvf/metrics/map_iou.py
torchvf/models/__init__.py
torchvf/models/decoder.py
torchvf/models/encoder.py
torchvf/models/models.py
torchvf/models/modules.py
torchvf/numerics/__init__.py
torchvf/numerics/affinity.py
torchvf/numerics/differentiation/__init__.py
torchvf/numerics/differentiation/finite_differences.py
torchvf/numerics/differentiation/kernels.py
torchvf/numerics/integration/__init__.py
torchvf/numerics/integration/ivp_int.py
torchvf/numerics/integration/solvers.py
torchvf/numerics/integration/utils.py
torchvf/numerics/interpolation/__init__.py
torchvf/numerics/interpolation/functional.py
torchvf/numerics/interpolation/interp_vf.py
torchvf/numerics/vector_fields.py
torchvf/transforms/__init__.py
torchvf/transforms/functional.py
torchvf/transforms/transforms.py
torchvf/utils/__init__.py
torchvf/utils/clustering.py
torchvf/utils/logger.py
torchvf/utils/tiling/__init__.py
torchvf/utils/tiling/base.py
torchvf/utils/tiling/dynamic_overlap.py
torchvf/utils/tiling/padding.py
torchvf/utils/tiling/reshape.py
torchvf/utils/utils.py
torchvf-0.1.3.dist-info/LICENSE
torchvf-0.1.3.dist-info/WHEEL
torchvf-0.1.3.dist-info/METADATA
torchvf-0.1.3.dist-info/RECORD
