Metadata-Version: 2.1
Name: torchvf
Version: 0.1.3
Summary: Vector fields for instance segmentation in PyTorch.
Home-page: https://github.com/ryanirl/torchvf
License: Apache-2.0
Author: Ryan Peters
Author-email: RyanIRL@icloud.com
Requires-Python: >=3.7,<4.0
Classifier: Development Status :: 2 - Pre-Alpha
Classifier: License :: OSI Approved :: Apache Software License
Classifier: Programming Language :: Python :: 3
Classifier: Programming Language :: Python :: 3 :: Only
Classifier: Programming Language :: Python :: 3.10
Classifier: Programming Language :: Python :: 3.7
Classifier: Programming Language :: Python :: 3.8
Classifier: Programming Language :: Python :: 3.9
Classifier: Topic :: Scientific/Engineering :: Artificial Intelligence
Requires-Dist: edt
Requires-Dist: matplotlib
Requires-Dist: numpy
Requires-Dist: opencv-python-headless
Requires-Dist: pandas
Requires-Dist: pyyaml
Requires-Dist: scikit-learn
Requires-Dist: torch (>=1.6.0,<2.1.0)
Requires-Dist: torchvision
Project-URL: Repository, https://github.com/ryanirl/torchvf
